{
  "parent": "minecraft:recipes/root",
  "rewards": {
    "recipes": [
      "secretdoors:secret_polished_diorite_trapdoor"
    ]
  },
  "criteria": {
    "has_polished_diorite": {
      "trigger": "minecraft:inventory_changed",
      "conditions": {
        "items": [
          {
            "items": [
              "minecraft:polished_diorite"
            ]
          }
        ]
      }
    },
    "has_the_recipe": {
      "trigger": "minecraft:recipe_unlocked",
      "conditions": {
        "recipe": "secretdoors:secret_polished_diorite_trapdoor"
      }
    }
  },
  "requirements": [
    [
      "has_polished_diorite",
      "has_the_recipe"
    ]
  ]
}